benchmarks/3_compare_encoders_perfs.py
benchmarks/__init__.py
benchmarks/bench_minhash_batch.py
benchmarks/benchmark_fuzzy_join_hash.py
benchmarks/encoders_time_memory_bench.py
benchmarks/fuzzy_join_benchmark.py
benchmarks/fuzzy_join_full_benchmark.py
benchmarks/get_results.py
benchmarks/similarity_scores_time_benchmark.py
benchmarks/tablevectorizer_tuning.py
benchmarks/utils/__init__.py
benchmarks/utils/_argparser.py
benchmarks/utils/_various.py
benchmarks/utils/monitor.py
dirty_cat/VERSION.txt
dirty_cat/__init__.py
dirty_cat/_check_dependencies.py
dirty_cat/_datetime_encoder.py
dirty_cat/_deduplicate.py
dirty_cat/_fast_hash.py
dirty_cat/_feature_augmenter.py
dirty_cat/_fuzzy_join.py
dirty_cat/_gap_encoder.py
dirty_cat/_minhash_encoder.py
dirty_cat/_similarity_encoder.py
dirty_cat/_string_distances.py
dirty_cat/_table_vectorizer.py
dirty_cat/_target_encoder.py
dirty_cat/_utils.py
dirty_cat/datasets/__init__.py
dirty_cat/datasets/_fetching.py
dirty_cat/datasets/_generating.py
dirty_cat/datasets/_ken_embeddings.py
dirty_cat/datasets/_utils.py
dirty_cat/datasets/tests/__init__.py
dirty_cat/datasets/tests/test_fetching.py
dirty_cat/datasets/tests/test_generating.py
dirty_cat/datasets/tests/test_ken_embeddings.py
dirty_cat/datasets/tests/test_utils.py
dirty_cat/tests/__init__.py
dirty_cat/tests/test_datetime_encoder.py
dirty_cat/tests/test_deduplicate.py
dirty_cat/tests/test_docstrings.py
dirty_cat/tests/test_fast_hash.py
dirty_cat/tests/test_feature_augmenter.py
dirty_cat/tests/test_fuzzy_join.py
dirty_cat/tests/test_gap_encoder.py
dirty_cat/tests/test_minhash_encoder.py
dirty_cat/tests/test_similarity_encoder.py
dirty_cat/tests/test_sklearn.py
dirty_cat/tests/test_string_distances.py
dirty_cat/tests/test_table_vectorizer.py
dirty_cat/tests/test_target_encoder.py
dirty_cat/tests/test_utils.py
dirty_cat/tests/utils.py
dirty_cat-0.4.1.dist-info/LICENSE.txt
dirty_cat-0.4.1.dist-info/METADATA
dirty_cat-0.4.1.dist-info/WHEEL
dirty_cat-0.4.1.dist-info/top_level.txt
dirty_cat-0.4.1.dist-info/RECORD
