Metadata-Version: 2.1
Name: dirty-cat
Version: 0.4.1
Summary: Machine learning with dirty categories.
Author: Patricio Cerda
Author-email: patricio.cerda@inria.fr
License: BSD
Project-URL: Homepage, https://dirty-cat.github.io/
Project-URL: Source, https://github.com/dirty-cat/dirty_cat
Classifier: Development Status :: 5 - Production/Stable
Classifier: Environment :: Console
Classifier: Intended Audience :: Science/Research
Classifier: License :: OSI Approved :: BSD License
Classifier: Operating System :: OS Independent
Classifier: Programming Language :: Python :: 3.8
Classifier: Programming Language :: Python :: 3.9
Classifier: Programming Language :: Python :: 3.10
Classifier: Topic :: Scientific/Engineering
Classifier: Topic :: Software Development :: Libraries
Requires-Python: >=3.8
Provides-Extra: dev
Provides-Extra: doc
Provides-Extra: benchmarks
Provides-Extra: min-py38
Provides-Extra: min-py39
Provides-Extra: min-py310
License-File: LICENSE.txt
